junkdraw/__init__.py
junkdraw/file_writer.py
junkdraw/run.py
junkdraw-0.1.0.dist-info/entry_points.txt
junkdraw-0.1.0.dist-info/WHEEL
junkdraw-0.1.0.dist-info/METADATA
junkdraw-0.1.0.dist-info/RECORD
