Metadata-Version: 2.1
Name: junkdraw
Version: 0.1.0
Summary: 
Author: Hugh Wimberly
Author-email: hugh.wimberly@gmail.com
Requires-Python: >=3.7,<4.0
Classifier: Programming Language :: Python :: 3
Classifier: Programming Language :: Python :: 3.7
Classifier: Programming Language :: Python :: 3.8
Classifier: Programming Language :: Python :: 3.9
Classifier: Programming Language :: Python :: 3.10
Classifier: Programming Language :: Python :: 3.11
